red_connector_http/__init__.py
red_connector_http/commons/__init__.py
red_connector_http/commons/cli_modes.py
red_connector_http/commons/helpers.py
red_connector_http/commons/schemas.py
red_connector_http/http/__init__.py
red_connector_http/http/__main__.py
red_connector_http/http/main.py
red_connector_http/http/mount_dir.py
red_connector_http/http/receive_dir.py
red_connector_http/http/send_receive_file.py
red_connector_http/http_archive/__init__.py
red_connector_http/http_archive/__main__.py
red_connector_http/http_archive/main.py
red_connector_http/http_archive/receive_dir.py
red_connector_http/http_json/__init__.py
red_connector_http/http_json/__main__.py
red_connector_http/http_json/main.py
red_connector_http/http_json/send_receive_file.py
red_connector_http/version.py
red_connector_http-1.0.dist-info/entry_points.txt
red_connector_http-1.0.dist-info/LICENSE
red_connector_http-1.0.dist-info/WHEEL
red_connector_http-1.0.dist-info/METADATA
red_connector_http-1.0.dist-info/RECORD
